vmjuggler/__init__.py
vmjuggler/base_objects.py
vmjuggler/exceptions.py
vmjuggler/helpers.py
vmjuggler-0.1.1.dist-info/LICENSE
vmjuggler-0.1.1.dist-info/METADATA
vmjuggler-0.1.1.dist-info/WHEEL
vmjuggler-0.1.1.dist-info/top_level.txt
vmjuggler-0.1.1.dist-info/RECORD
