Metadata-Version: 2.1
Name: vmjuggler
Version: 0.1.1
Summary: vmjuggler provides the simple high level API to VMWare’s SDK.
Home-page: https://github.com/shurkam/vmjuggler
Author: Alexandr Malygin
Author-email: shurkam@gmail.com
Project-URL: Documentation, https://vmjuggler.readthedocs.io/en/latest/
Project-URL: Bug Reports, https://github.com/shurkam/vmjuggler/issues
Project-URL: Source, https://github.com/shurkam/vmjuggler/
Keywords: vmware pyvmomi vm vcenter API devops sdk
Classifier: Development Status :: 4 - Beta
Classifier: Intended Audience :: Developers
Classifier: Topic :: Software Development :: Build Tools
Classifier: License :: OSI Approved :: MIT License
Classifier: Programming Language :: Python :: 3
Classifier: Programming Language :: Python :: 3.7
Classifier: Programming Language :: Python :: 3.8
Classifier: Programming Language :: Python :: 3.9
Classifier: Programming Language :: Python :: 3.10
Classifier: Programming Language :: Python :: 3.11
License-File: LICENSE
Requires-Dist: pyvmomi >=6.5
